{
	"info": {
		"_postman_id": "f9cf2182-6b2d-4ce5-901c-594751ab8082",
		"name": "ToDo List",
		"schema": "https://schema.getpostman.com/json/collection/v2.1.0/collection.json",
		"_exporter_id": "4134803"
	},
	"item": [
		{
			"name": "00. Hello World",
			"request": {
				"method": "GET",
				"header": [],
				"url": {
					"raw": "{{host}}",
					"host": [
						"{{host}}"
					]
				}
			},
			"response": []
		},
		{
			"name": "01. Register",
			"request": {
				"method": "POST",
				"header": [],
				"body": {
					"mode": "raw",
					"raw": "{\n    \"login\": \"test\",\n    \"email\": \"test@test.com\",\n    \"password\": \"qwe123\"\n}",
					"options": {
						"raw": {
							"language": "json"
						}
					}
				},
				"url": {
					"raw": "{{host}}/register",
					"host": [
						"{{host}}"
					],
					"path": [
						"register"
					]
				}
			},
			"response": []
		},
		{
			"name": "02. Login",
			"request": {
				"method": "POST",
				"header": [],
				"body": {
					"mode": "raw",
					"raw": "{\n    \"login\": \"test\",\n    \"password\": \"qwe123\"\n}",
					"options": {
						"raw": {
							"language": "json"
						}
					}
				},
				"url": {
					"raw": "{{host}}/login",
					"host": [
						"{{host}}"
					],
					"path": [
						"login"
					]
				}
			},
			"response": []
		},
		{
			"name": "03. Create a list",
			"request": {
				"method": "POST",
				"header": [],
				"body": {
					"mode": "raw",
					"raw": "{\n    \"title\": \"my list 1\",\n    \"description\": \"list description 1\"\n}",
					"options": {
						"raw": {
							"language": "json"
						}
					}
				},
				"url": {
					"raw": "{{host}}/lists",
					"host": [
						"{{host}}"
					],
					"path": [
						"lists"
					]
				}
			},
			"response": []
		},
		{
			"name": "04. Get my lists",
			"request": {
				"method": "GET",
				"header": [],
				"url": {
					"raw": "{{host}}/lists",
					"host": [
						"{{host}}"
					],
					"path": [
						"lists"
					]
				}
			},
			"response": []
		},
		{
			"name": "05. Get current user",
			"request": {
				"method": "GET",
				"header": [],
				"url": {
					"raw": "{{host}}/user",
					"host": [
						"{{host}}"
					],
					"path": [
						"user"
					]
				}
			},
			"response": []
		},
		{
			"name": "06. Update current user",
			"request": {
				"method": "PATCH",
				"header": [],
				"body": {
					"mode": "raw",
					"raw": "{\n    \"user\": {\n    \"username\": \"Maksimka\"\n}\n}",
					"options": {
						"raw": {
							"language": "json"
						}
					}
				},
				"url": {
					"raw": "{{host}}/user",
					"host": [
						"{{host}}"
					],
					"path": [
						"user"
					]
				}
			},
			"response": []
		}
	],
	"event": [
		{
			"listen": "prerequest",
			"script": {
				"type": "text/javascript",
				"packages": {},
				"exec": [
					""
				]
			}
		},
		{
			"listen": "test",
			"script": {
				"type": "text/javascript",
				"packages": {},
				"exec": [
					""
				]
			}
		}
	],
	"variable": [
		{
			"key": "host",
			"value": "0.0.0.0",
			"type": "string"
		}
	]
}